rtplot/__init__.py
rtplot/core/__init__.py
rtplot/core/helpers.py
rtplot/core/internal.py
rtplot/core/main.py
rtplot/core/version.py
rtplot/examples/__init__.py
rtplot/examples/rand_data_generators.py
rtplot/examples/timeseries_example.py
rtplot/examples/xy_example.py
rtplot/shortcuts/__init__.py
rtplot/shortcuts/line.py
rtplot/shortcuts/shape.py
rtplot-2.1.2.dist-info/LICENSE
rtplot-2.1.2.dist-info/METADATA
rtplot-2.1.2.dist-info/WHEEL
rtplot-2.1.2.dist-info/top_level.txt
rtplot-2.1.2.dist-info/RECORD
