Metadata-Version: 2.1
Name: rtplot
Version: 2.1.2
Summary: Real time plotting. Yes, you can do it now.
Home-page: https://github.com/nabeelsherazi/rtplot
Author: Nabeel Sherazi
Author-email: sherazi.n@husky.neu.edu
License: UNKNOWN
Platform: UNKNOWN
Classifier: Programming Language :: Python :: 3
Classifier: License :: OSI Approved :: MIT License
Classifier: Operating System :: OS Independent
Classifier: Development Status :: 3 - Alpha
Classifier: Framework :: Matplotlib
Classifier: Intended Audience :: Science/Research
Requires-Python: >=3.6
Requires-Dist: matplotlib (==3.1.3)
Requires-Dist: numpy (>=1.18.1)
